msp2lib/Dockerfile
msp2lib/__init__.py
msp2lib/__main__.py
msp2lib/core.py
msp2lib/make_nistlib.sh
msp2lib/utils.py
msp2lib/__pycache__/__init__.cpython-36.pyc
msp2lib/__pycache__/core.cpython-36.pyc
msp2lib/__pycache__/utils.cpython-36.pyc
msp2lib-0.1.3.dist-info/LICENSE
msp2lib-0.1.3.dist-info/METADATA
msp2lib-0.1.3.dist-info/WHEEL
msp2lib-0.1.3.dist-info/entry_points.txt
msp2lib-0.1.3.dist-info/top_level.txt
msp2lib-0.1.3.dist-info/RECORD
