Metadata-Version: 2.1
Name: msp2lib
Version: 0.1.3
Summary: Convert an MSP file representing one or more Mass Spectra to a NIST MS Search user library.
Home-page: https://github.com/domdfcoding/msp2lib
Author: Dominic Davis-Foster
Author-email: dominic@davis-foster.co.uk
License: LGPLv3
Platform: UNKNOWN
Classifier: Development Status :: 3 - Alpha
Classifier: Environment :: Console
Classifier: Operating System :: POSIX :: Linux
Classifier: Intended Audience :: Developers
Classifier: Intended Audience :: End Users/Desktop
Classifier: Intended Audience :: Science/Research
Classifier: License :: OSI Approved :: GNU Lesser General Public License v3 or later (LGPLv3+)
Classifier: Programming Language :: Python
Classifier: Programming Language :: Python :: 3.6
Classifier: Programming Language :: Python :: 3.7
Classifier: Programming Language :: Python :: 3.8
Classifier: Topic :: Software Development :: Libraries :: Python Modules
